zen_core/__init__.py
zen_core/configuration/__init__.py
zen_core/configuration/config_reader.py
zen_core/handlers/__init__.py
zen_core/handlers/access_controlled_git_object.py
zen_core/handlers/git_client.py
zen_core/handlers/git_config.py
zen_core/handlers/git_org.py
zen_core/handlers/git_repo.py
zen_core/handlers/git_team.py
zen_core/handlers/git_user.py
zen_core/handlers/named_git_object.py
zen_core/logging/__init__.py
zen_core/logging/printer.py
zen_core/parsing/__init__.py
zen_core/parsing/group_config.py
zen_core/parsing/org_config.py
zen_core/parsing/repo_config.py
zen_core/parsing/team_config.py
zen_core/parsing/toml_parser.py
zen_core-0.2.7.dist-info/LICENSE
zen_core-0.2.7.dist-info/WHEEL
zen_core-0.2.7.dist-info/METADATA
zen_core-0.2.7.dist-info/RECORD
